grasping_type_inference/__init__.py
grasping_type_inference/definitions.py
grasping_type_inference/face.py
grasping_type_inference/grasping_type_mln.py
grasping_type_inference/ground_atom_builder.py
grasping_type_inference/inference.py
grasping_type_inference/learning.py
grasping_type_inference/grasping_object/__init__.py
grasping_type_inference/grasping_object/grasping_object.py
grasping_type_inference/grasping_object/orientation.py
grasping_type_inference/grasping_object/rotationally_symmetrical_grasping_object.py
grasping_type_inference/mln/grasping_type.pracmln
grasping_type_inference/test/__init__.py
grasping_type_inference/test/inference_test.py
grasping_type_inference/test/learning_test.py
grasping_type_inference-1.0.3.dist-info/LICENSE
grasping_type_inference-1.0.3.dist-info/METADATA
grasping_type_inference-1.0.3.dist-info/WHEEL
grasping_type_inference-1.0.3.dist-info/top_level.txt
grasping_type_inference-1.0.3.dist-info/RECORD
