Metadata-Version: 2.1
Name: grasping-type-inference
Version: 1.0.3
Summary: Utilizes a Markov Logic Network to infer the most probable grasping type for a defined object
Home-page: https://github.com/code-iai/iai-grasping-type-inference
Author: Sebastian Koralewski
Author-email: seba@cs.uni-bremen.de
License: UNKNOWN
Platform: UNKNOWN
Classifier: Programming Language :: Python :: 2
Classifier: License :: OSI Approved :: MIT License
Classifier: Operating System :: OS Independent
Requires-Dist: high-level-markov-logic-network (==1.0.1)
